MANIFEST.in
setup.py
magicmock/Exceptions.py
magicmock/Utils.py
magicmock/__init__.py
magicmock.egg-info/PKG-INFO
magicmock.egg-info/SOURCES.txt
magicmock.egg-info/dependency_links.txt
magicmock.egg-info/entry_points.txt
magicmock.egg-info/not-zip-safe
magicmock.egg-info/requires.txt
magicmock.egg-info/top_level.txt
magicmock/ClientAPI/__init__.py
magicmock/Http/HttpController.py
magicmock/Http/HttpHandler.py
magicmock/Http/JsonHandler.py
magicmock/Http/MockController.py
magicmock/Http/__init__.py
magicmock/Http/web/__init__.py
magicmock/Http/web/application.py
magicmock/Http/web/browser.py
magicmock/Http/web/db.py
magicmock/Http/web/debugerror.py
magicmock/Http/web/form.py
magicmock/Http/web/http.py
magicmock/Http/web/httpserver.py
magicmock/Http/web/mockserver.py
magicmock/Http/web/net.py
magicmock/Http/web/python23.py
magicmock/Http/web/session.py
magicmock/Http/web/template.py
magicmock/Http/web/test.py
magicmock/Http/web/utils.py
magicmock/Http/web/webapi.py
magicmock/Http/web/webopenid.py
magicmock/Http/web/wsgi.py
magicmock/Http/web/contrib/__init__.py
magicmock/Http/web/contrib/template.py
magicmock/Http/web/wsgiserver/LICENSE.txt
magicmock/Http/web/wsgiserver/__init__.py
magicmock/Http/web/wsgiserver/ssl_builtin.py
magicmock/Http/web/wsgiserver/ssl_pyopenssl.py
magicmock/Log/Log.py
magicmock/Log/__init__.py
magicmock/Sample/__init__.py
magicmock/Sample/APITemplates/__init__.py
magicmock/Sample/APITemplates/key_value_one_two.py
magicmock/Sample/JsonTemplates/key_value_one_two.json
magicmock/Sample/conf/mockserver.cfg
magicmock/Sample/ssl/certnew.cer
magicmock/Sample/ssl/certnew.p7b
magicmock/Sample/ssl/client.csr
magicmock/Sample/ssl/client.key