Metadata-Version: 1.0
Name: magicmock
Version: 0.02
Summary: A generic mock server
Home-page: https://github.com/mzxu/magicmock
Author: Mingze
Author-email: mzxu@outlook.com
License: MIT
Platform: UNKNOWN
